nodeps.pth
nodeps/__init__.py
nodeps/__main__.py
nodeps/_post_install.py
nodeps/backend.py
nodeps/nodeps.pth
nodeps/data/Brewfile
nodeps/extras/__init__.py
nodeps/extras/_echo.py
nodeps/extras/_echo.pyi
nodeps/extras/ansi.py
nodeps/extras/debug.py
nodeps/extras/echo.py
nodeps/extras/log.py
nodeps/extras/log.pyi
nodeps/extras/pickle.py
nodeps/extras/pretty.py
nodeps/extras/repo.py
nodeps/extras/repo.pyi
nodeps/extras/url.py
nodeps/fixtures/__init__.py
nodeps/ipython_dir/extensions/ex.py
nodeps/ipython_dir/extensions/reload.py
nodeps/ipython_dir/profile_default/ipython_config.py
nodeps/ipython_dir/profile_default/ipython_pycharm_startup.py
nodeps/ipython_dir/profile_default/python_startup.py
nodeps/ipython_dir/profile_default/backup/ipython_config.py
nodeps/ipython_dir/profile_default/startup/README
nodeps/ipython_dir/profile_default/startup/import_all.py
nodeps/ipython_dir/profile_default/startup/startup.ipy
nodeps/ipython_dir/profile_default/startup/user_ns.py
nodeps/ipython_variables/__init__.py
nodeps/modules/__init__.py
nodeps/modules/classes.py
nodeps/modules/constants.py
nodeps/modules/datas.py
nodeps/modules/enums.py
nodeps/modules/env.py
nodeps/modules/errors.py
nodeps/modules/functions.py
nodeps/modules/gh.py
nodeps/modules/metapath.py
nodeps/modules/path.py
nodeps/modules/path.pyi
nodeps/modules/project.py
nodeps/modules/seteuid.py
nodeps/modules/typings.py
nodeps/modules/platforms/__init__.py
nodeps/modules/platforms/assembla.py
nodeps/modules/platforms/base.py
nodeps/modules/platforms/bitbucket.py
nodeps/modules/platforms/friendcode.py
nodeps/modules/platforms/github.py
nodeps/modules/platforms/gitlab.py
nodeps/setup/__init__.py
nodeps/variables/builtin.py
nodeps-0.3.3.data/scripts/git-branch-default-update
nodeps-0.3.3.data/scripts/git-can-admin
nodeps-0.3.3.data/scripts/git-mod-add
nodeps-0.3.3.data/scripts/git-mod-clean
nodeps-0.3.3.data/scripts/git-mod-rm
nodeps-0.3.3.data/scripts/git-owner-update
nodeps-0.3.3.data/scripts/git-projects-push
nodeps-0.3.3.dist-info/LICENSE
nodeps-0.3.3.dist-info/METADATA
nodeps-0.3.3.dist-info/WHEEL
nodeps-0.3.3.dist-info/entry_points.txt
nodeps-0.3.3.dist-info/top_level.txt
nodeps-0.3.3.dist-info/RECORD
