Metadata-Version: 2.1
Name: nodeps
Version: 0.3.3
Summary: Python helpers and utilities with no dependencies
Author-email: José Antonio Puértolas Montañés <159632576+j5pu@users.noreply.github.com>
License: MIT
Project-URL: Homepage, https://github.com/j5pu/nodeps
Project-URL: Documentation, https://nodeps.readthedocs.io
Classifier: Framework :: Pytest
Requires-Python: >=3.11
License-File: LICENSE
Provides-Extra: all
Requires-Dist: nodeps[ansi] ; extra == 'all'
Requires-Dist: nodeps[cli] ; extra == 'all'
Requires-Dist: nodeps[echo] ; extra == 'all'
Requires-Dist: nodeps[env] ; extra == 'all'
Requires-Dist: nodeps[ipython] ; extra == 'all'
Requires-Dist: nodeps[log] ; extra == 'all'
Requires-Dist: nodeps[pickle] ; extra == 'all'
Requires-Dist: nodeps[pretty] ; extra == 'all'
Requires-Dist: nodeps[pth] ; extra == 'all'
Requires-Dist: nodeps[repo] ; extra == 'all'
Requires-Dist: nodeps[requests] ; extra == 'all'
Provides-Extra: ansi
Requires-Dist: strip-ansi <1,>=0.1.1 ; extra == 'ansi'
Provides-Extra: cli
Requires-Dist: tomlkit <1,>=0.12.1 ; extra == 'cli'
Requires-Dist: typer[all] <1,>=0.9 ; extra == 'cli'
Provides-Extra: dev
Requires-Dist: build <2,>=1.0.3 ; extra == 'dev'
Requires-Dist: hunter <4,>=3.6.1 ; extra == 'dev'
Requires-Dist: icecream <3,>=2.1.3 ; extra == 'dev'
Requires-Dist: nodeps[ipython] ; extra == 'dev'
Requires-Dist: twine <5,>=4.0.2 ; extra == 'dev'
Requires-Dist: tomlkit <1,>=0.12.1 ; extra == 'dev'
Requires-Dist: docrepr <1,>=0.2.0 ; extra == 'dev'
Requires-Dist: docutils ; extra == 'dev'
Requires-Dist: furo <2024,>=2023.9.10 ; extra == 'dev'
Requires-Dist: myst-parser <3,>=2.0.0 ; extra == 'dev'
Requires-Dist: sphinx <8,>=7.2.6 ; extra == 'dev'
Requires-Dist: sphinx-autodoc-typehints ; extra == 'dev'
Requires-Dist: sphinx-autobuild <2022,>=2021.3.14 ; extra == 'dev'
Requires-Dist: sphinx-click <6,>=5.0.1 ; extra == 'dev'
Requires-Dist: sphinxcontrib-napoleon <1,>=0.7 ; extra == 'dev'
Requires-Dist: coverage[toml] <8,>=7.3.2 ; extra == 'dev'
Requires-Dist: darglint <2,>=1.8.1 ; extra == 'dev'
Requires-Dist: environs <10,>=9.5.0 ; extra == 'dev'
Requires-Dist: pycodestyle <3,>=2.11.0 ; extra == 'dev'
Requires-Dist: pydocstyle <7,>=6.3 ; extra == 'dev'
Requires-Dist: pytest <8,>=7 ; extra == 'dev'
Requires-Dist: pytest-asyncio <1,>=0.21.1 ; extra == 'dev'
Requires-Dist: pytest-clarity <2,>=1.0.1 ; extra == 'dev'
Requires-Dist: pytest-cov <5,>=4 ; extra == 'dev'
Requires-Dist: pytest-xdist <3,>=2 ; extra == 'dev'
Requires-Dist: pytest-sugar <1,>=0.9.7 ; extra == 'dev'
Requires-Dist: ruff <0.1,>=0.0.282 ; extra == 'dev'
Requires-Dist: ruff-lsp <0.1,>=0.0.39 ; extra == 'dev'
Requires-Dist: tox <5,>=4.6.4 ; extra == 'dev'
Requires-Dist: black[d] <24,>=23.9.1 ; (python_version < "3.12") and extra == 'dev'
Provides-Extra: echo
Requires-Dist: typer[all] <1,>=0.9 ; extra == 'echo'
Provides-Extra: env
Requires-Dist: python-decouple <4,>=3.8 ; extra == 'env'
Provides-Extra: full
Requires-Dist: nodeps[all] ; extra == 'full'
Requires-Dist: nodeps[dev] ; extra == 'full'
Provides-Extra: ipython
Requires-Dist: ipython <9,>=8.16.0 ; extra == 'ipython'
Requires-Dist: nodeps[pretty] ; extra == 'ipython'
Requires-Dist: pickleshare ; extra == 'ipython'
Provides-Extra: log
Requires-Dist: loguru <1,>=0.7.2 ; extra == 'log'
Provides-Extra: pickle
Requires-Dist: jsonpickle <4,>=3.0.2 ; extra == 'pickle'
Requires-Dist: structlog <24,>=23.1.0 ; extra == 'pickle'
Provides-Extra: pretty
Requires-Dist: rich <14,>=13.6.0 ; extra == 'pretty'
Provides-Extra: pth
Requires-Dist: setuptools <69,>=68.2.2 ; extra == 'pth'
Provides-Extra: repo
Requires-Dist: gitpython <4,>=3.1.37 ; extra == 'repo'
Provides-Extra: requests
Requires-Dist: beautifulsoup4 <5,>=4.12.2 ; extra == 'requests'
Requires-Dist: requests <3,>=2.31.0 ; extra == 'requests'
Requires-Dist: urllib3[socks] ; extra == 'requests'
